{"data": [{"ObjectIdentifier": "S-1-5-21-917908876-1423158569-3159038727", "Properties": {"name": "CICADA.HTB", "domain": "CICADA.HTB", "domainsid": "S-1-5-21-917908876-1423158569-3159038727", "distinguishedname": "DC=CICADA,DC=HTB", "description": "", "functionallevel": "2016", "highvalue": true, "whencreated": 1710414553}, "Trusts": [], "Aces": [{"RightName": "Owns", "IsInherited": false, "PrincipalSID": "CICADA.HTB-S-1-5-32-544", "PrincipalType": "Group"}, {"RightName": "GetChanges", "IsInherited": false, "PrincipalSID": "S-1-5-21-917908876-1423158569-3159038727-498", "PrincipalType": "Group"}, {"RightName": "GetChangesAll", "IsInherited": false, "PrincipalSID": "S-1-5-21-917908876-1423158569-3159038727-516", "PrincipalType": "Group"}, {"RightName": "GetChangesInFilteredSet", "IsInherited": false, "PrincipalSID": "CICADA.HTB-S-1-5-32-544", "PrincipalType": "Group"}, {"RightName": "GetChanges", "IsInherited": false, "PrincipalSID": "CICADA.HTB-S-1-5-32-544", "PrincipalType": "Group"}, {"RightName": "GetChangesAll", "IsInherited": false, "PrincipalSID": "CICADA.HTB-S-1-5-32-544", "PrincipalType": "Group"}, {"RightName": "GetChangesInFilteredSet", "IsInherited": false, "PrincipalSID": "CICADA.HTB-S-1-5-9", "PrincipalType": "Group"}, {"RightName": "GetChanges", "IsInherited": false, "PrincipalSID": "CICADA.HTB-S-1-5-9", "PrincipalType": "Group"}, {"RightName": "WriteOwner", "IsInherited": false, "PrincipalSID": "S-1-5-21-917908876-1423158569-3159038727-512", "PrincipalType": "Group"}, {"RightName": "AllExtendedRights", "IsInherited": false, "PrincipalSID": "S-1-5-21-917908876-1423158569-3159038727-512", "PrincipalType": "Group"}, {"RightName": "WriteDacl", "IsInherited": false, "PrincipalSID": "S-1-5-21-917908876-1423158569-3159038727-512", "PrincipalType": "Group"}, {"RightName": "GenericAll", "IsInherited": false, "PrincipalSID": "S-1-5-21-917908876-1423158569-3159038727-519", "PrincipalType": "Group"}, {"RightName": "WriteOwner", "IsInherited": false, "PrincipalSID": "CICADA.HTB-S-1-5-32-544", "PrincipalType": "Group"}, {"RightName": "AllExtendedRights", "IsInherited": false, "PrincipalSID": "CICADA.HTB-S-1-5-32-544", "PrincipalType": "Group"}, {"RightName": "WriteDacl", "IsInherited": false, "PrincipalSID": "CICADA.HTB-S-1-5-32-544", "PrincipalType": "Group"}], "Links": [{"IsEnforced": true, "GUID": "5D96E416-A941-4E66-9F79-880604750A79"}, {"IsEnforced": true, "GUID": "4F093950-80DE-4377-932E-06A09555C803"}], "ChildObjects": [{"ObjectIdentifier": "C1ED733D-CD04-4A33-A54E-4E4A2706E7B5", "ObjectType": "Container"}, {"ObjectIdentifier": "F98079FF-B2F4-4A26-9B56-778AA427FC9C", "ObjectType": "Container"}, {"ObjectIdentifier": "S-1-5-21-917908876-1423158569-3159038727-1103", "ObjectType": "Group"}, {"ObjectIdentifier": "C7077455-E292-41CE-AABB-F65B4FF9A118", "ObjectType": "OU"}, {"ObjectIdentifier": "C5F7239F-9EAD-4272-B9FB-74FFABF5953A", "ObjectType": "Container"}, {"ObjectIdentifier": "40113203-CC1D-4D35-85D4-2D4095B315C9", "ObjectType": "OU"}, {"ObjectIdentifier": "9383096A-14B4-48A6-85D0-CE484FE9B7B5", "ObjectType": "Container"}], "GPOChanges": {"AffectedComputers": [], "DcomUsers": [], "LocalAdmins": [], "PSRemoteUsers": [], "RemoteDesktopUsers": []}, "IsDeleted": false, "IsACLProtected": false}], "meta": {"type": "domains", "count": 1, "version": 5}}